<resources language="ru">
  <group>Group</group>
  <group_description>You can see all group participants on a map, they could also you, if you have enabled 'Sending your locations'.<br />
  You can plan trips, prepare route points and route tracks for live and integrated navigation on many devices.</group_description>
  <with_osmodroid>Monitor via OsMoDroid</with_osmodroid>
  <with_osmodroid_description>Our official client gives maximum possibilities to work with service</with_osmodroid_description>
  <with_osmand>Use OsmAnd</with_osmand>
  <with_osmand_description>Для навигационной программы OsmAnd есть свой плагин OsMo, позволяющий работать с функциями сервиса внутри удобной навигационной оболочки</with_osmand_description>
  <with_website>Access through on the website</with_website>
  <with_website_description>Это легкий и простой доступ для просмотра и управления, через любой удобный вам интернет-браузер</with_website_description>
</resources>
