<resources language="ru">
  <group>Группы</group>
  <group_description>Вы видите всех участников группы на единой карте, они также видят вас, когда у вас активна передача местоположений.<br />
  Можно планировать поездки, накладывать точки и треки для удобной одновременной навигации множества устройств.</group_description>
  <with_osmodroid>Наблюдайте через OsMoDroid</with_osmodroid>
  <with_osmodroid_description>Наш официальный клиент даёт максимум возможностей по работе с сервисом</with_osmodroid_description>
  <with_osmand>Используйте OsmAnd</with_osmand>
  <with_osmand_description>Для навигационной программы OsmAnd есть свой плагин OsMo, позволяющий работать с функциями сервиса внутри удобной навигационной оболочки</with_osmand_description>
  <with_website>Работайте через сайт</with_website>
  <with_website_description>Это легкий и простой доступ для просмотра и управления, через любой удобный вам интернет-браузер</with_website_description>
  <group_add>Создать группу</group_add>
  <group_catalog>Каталог групп</group_catalog>
  <group_catalog_description>Здесь собраны крупные и открытые группы с нашего сайта. Вы можете найти подходящую вам и понаблюдать за ней.</group_catalog_description>  
  <group_no_latlon>Не заданы начальные координаты группы</group_no_latlon>
  <activity>Последняя активность</activity>
  <join_group>Вступить в группу</join_group>
  <join_note>Пожалуйста авторизуйтесь, чтобы вступать в группы через веб-сайт</join_note>
  <join_note_byid>Без авторизации вы можете присоединиться к группе через любое наше приложение по ID</join_note_byid>
  <you_in_group>Вы в группе</you_in_group>
  <you_joined>Вы в группе</you_joined>
</resources>